kokoroio/__init__.py
kokoroio/clients/__init__.py
kokoroio/clients/access_tokens.py
kokoroio/clients/bot.py
kokoroio/clients/channels.py
kokoroio/clients/client.py
kokoroio/clients/devices.py
kokoroio/clients/memberships.py
kokoroio/clients/profiles.py
kokoroio/utils/__init__.py
kokoroio/utils/config.py
kokoroio-0.0.3.dist-info/DESCRIPTION.rst
kokoroio-0.0.3.dist-info/METADATA
kokoroio-0.0.3.dist-info/RECORD
kokoroio-0.0.3.dist-info/WHEEL
kokoroio-0.0.3.dist-info/metadata.json
kokoroio-0.0.3.dist-info/top_level.txt
