Metadata-Version: 2.0
Name: kokoroio
Version: 0.0.3
Summary: Client for kokoro.io
Home-page: https://github.com/mtwtkman/kokoro-io-py
Author: mtwtkman
Author-email: UNKNOWN
License: WTFPL
Keywords: kokoro.io
Platform: UNKNOWN
Classifier: Programming Language :: Python :: 3.6
Requires-Python: >=3.6
Requires-Dist: requests
Requires-Dist: aiohttp
Provides-Extra: build
Requires-Dist: wheel; extra == 'build'
Provides-Extra: dev
Requires-Dist: flake8; extra == 'dev'
Requires-Dist: mypy-lang; extra == 'dev'
